[{"Color": "brown", "ID": 41, "Name": "Gold Rum", "Brands": ["Gold rum", "Appleton Estate V/X Jamaican rum", "Jamaican rum"], "Category": 0}, {"Color": "brown", "ID": 53, "Name": "overproof rum", "Brands": ["Bacardi 151"], "Category": 0}, {"Color": "brown", "ID": 54, "Name": "Light Rum", "Brands": ["Cruzan white rum", "Blackstrap rum", "Cuban light rum", "Havana Club white rum", "Light Rum", "Bacardi Gold Rum", "White rum", "Bacardi Anejo Rum", "Bacardi light rum"], "Category": 0}, {"Color": "brown", "ID": 57, "Name": "Coconut Rum", "Brands": ["Parrot Bay Rum", "Malibu coconut rum", "Coconut rum", "Parrot Bay coconut rum", "Bacardi Coco Rum", "Cruzan Mango Rum", "Cruzan Coconut Rum", "Malibu Mango Rum"], "Category": 0}, {"Color": "brown", "ID": 58, "Name": "Dark rum", "Brands": ["Dark rum", "Myer's Dark Rum", "Brown rum", "Bacardi dark rum", "Woods 100 dark rum", "Black rum", "Gosling's Black Seal rum"], "Category": 0}, {"Color": "brown", "ID": 59, "Name": "lemon-flavored rum", "Brands": ["Bacardi Limon Rum"], "Category": 0}, {"Color": "brown", "ID": 60, "Name": "orange-flavored rum", "Brands": ["Bacardi O"], "Category": 0}, {"Color": "brown", "ID": 61, "Name": "raspberry-flavored rum", "Brands": ["Bacardi Razz Rum"], "Category": 0}, {"Color": "brown", "ID": 65, "Name": "banana-flavored rum", "Brands": ["Banana rum"], "Category": 0}, {"Color": "brown", "ID": 132, "Name": "pineapple-flavered rum", "Brands": ["Captain Morgan Parrot Bay Pineapple Rum", "Pineapple Rum"], "Category": 0}, {"Color": "brown", "ID": 133, "Name": "spiced rum", "Brands": ["Kraken Rum", "Sailor Jerry Spiced Rum", "Marimba Spiced Breeze flavored rum", "Captain Morgan's spiced rum", "Spiced rum"], "Category": 0}, {"Color": "brown", "ID": 240, "Name": "dry rum", "Brands": ["Dry rum"], "Category": 0}, {"Color": "brown", "ID": 359, "Name": "Lemon Rum", "Brands": ["Lemon Rum"], "Category": 0}, {"Color": "brown", "ID": 554, "Name": "RedRum", "Brands": ["RedRum"], "Category": 0}, {"Color": "brown", "ID": 564, "Name": "Rum Tree", "Brands": ["Rum Tree"], "Category": 0}, {"Color": "brown", "ID": 577, "Name": "Silver Rum", "Brands": ["Silver Rum"], "Category": 0}, {"Color": "brown", "ID": 646, "Name": "Vanilla Rum", "Brands": ["Vanilla Rum"], "Category": 0}, {"Color": "brown", "ID": 87, "Name": "whiskey", "Brands": ["Jameson Black Barrel", "Teeling Irish Whiskey", "Connemara Irish Whiskey", "Jack Daniels Whiskey", "Scotch whiskey", "Canadian Club whisky", "Canadian whisky", "Cherry whiskey", "Jack Daniel's Tennessee whiskey", "Bushmills Irish Whiskey", "Macallan 12 year scotch", "Powers Irish whiskey", "McGuinness cherry whisky", "Tennessee Whiskey", "Crown Royal canadian whisky", "Johnny Walker Black Label Scotch", "Laphroaig", "Black Bush Irish Whisky", "Famous Grouse Scotch", "Jameson blended whiskey"], "Category": 0}, {"Color": "brown", "ID": 128, "Name": "pot-infused whiskey", "Brands": ["Pot-infused whiskey", "Cannabis-infused whiskey"], "Category": 0}, {"Color": "brown", "ID": 179, "Name": "Cinnamom Whiskey", "Brands": ["Cinnamon whiskey", "Fireball"], "Category": 0}, {"Color": "brown", "ID": 119, "Name": "Butterscotch Liqueur", "Brands": ["Butterscotch liqueur", "Du Bouchett Butterscotch Liqeueur", "DeKuyPer Butterscotch Schnapps Liqueur", "Gaetano Butterscotch Cream Liqueur"], "Category": 0}, {"Color": "brown", "ID": 120, "Name": "Butterscotch Schnapps", "Brands": ["Butterscotch Schnapps"], "Category": 0}, {"Color": "brown", "ID": 332, "Name": "Johnnie Walker Scotch", "Brands": ["Johnnie Walker Scotch"], "Category": 0}, {"Color": "brown", "ID": 63, "Name": "Bourbon", "Brands": ["Knob Creek Bourbon", "Woodford Reserve bourbon", "Peach juice", "Basil Hayden's bourbon", "Elijah Craig Bourbon", "Maker's Mark Bourbon", "Wild Turkey 101", "Booker's Bourbon", "Baker's bourbon", "Wild Turkey 101", "Bourbon"], "Category": 0}, {"Color": "brown", "ID": 331, "Name": "Jim Beam Bourbon", "Brands": ["Jim Beam Bourbon"], "Category": 0}, {"Color": "tan", "ID": 11, "Name": "Advocaat Liqueur", "Brands": ["Advocaat Liqueur", "Bols Advocaat"], "Category": 0}, {"Color": "tan", "ID": 17, "Name": "Alize Bleu Liqueur", "Brands": ["Alize Bleu Liqueur"], "Category": 0}, {"Color": "tan", "ID": 18, "Name": "Alize Gold Passion Liqueur", "Brands": ["Alize Gold Passion Liqueur"], "Category": 0}, {"Color": "tan", "ID": 19, "Name": "Alize Red Passion Liqueur", "Brands": ["Alize Red Passion Liqueur"], "Category": 0}, {"Color": "tan", "ID": 20, "Name": "Allspice Liqueur", "Brands": ["Allspice Liqueur"], "Category": 0}, {"Color": "tan", "ID": 22, "Name": "almond liqueur", "Brands": ["Swiss chocolate almond liqueur", "Almond liqueur", "Creme de almond", "Amaretto Di Saronno"], "Category": 0}, {"Color": "tan", "ID": 24, "Name": "Apricot Liqueur", "Brands": ["Amaretto Di Amore"], "Category": 0}, {"Color": "tan", "ID": 26, "Name": "cream liqueur", "Brands": ["RumChata", "Amarula", "Cream liqueur", "Irish Manor Legendary Irish Cream Liqueur", "Carolans Irish Cream Liqueur"], "Category": 0}, {"Color": "tan", "ID": 32, "Name": "anise liqueur", "Brands": ["Ouzo", "Anisette"], "Category": 0}, {"Color": "tan", "ID": 34, "Name": "Apple liqueur", "Brands": ["Apfelkorn Liqueur", "Apple Liqueur"], "Category": 0}, {"Color": "tan", "ID": 46, "Name": "apricot liqueur", "Brands": ["Apricot liqueur"], "Category": 0}, {"Color": "tan", "ID": 69, "Name": "Honey liqueur", "Brands": ["Drambuie", "Honey liqueur", "Krupnik honey liqueur", "Barenjager Liqueur"], "Category": 0}, {"Color": "tan", "ID": 72, "Name": "Hazelnut Liqueur", "Brands": ["Hazelnut Liqueur", "Frangelico hazelnut liqueur", "Basilica Hazelnut Liqueur", "Gaetano Hazelnut Liqueur", "Chocolate Hazelnut Liqueur"], "Category": 0}, {"Color": "tan", "ID": 73, "Name": "Coconut Liqueur", "Brands": ["Coconut liqueur", "Creme de coconut", "Malibu coconut liqueur", "Batida de Coco"], "Category": 0}, {"Color": "tan", "ID": 80, "Name": "benedictine herbal liqueur", "Brands": ["Benedictine"], "Category": 0}, {"Color": "tan", "ID": 85, "Name": "blackberry liqueur", "Brands": ["Marie Brizzard", "Echte Kroatzbeere", "Blackberry liqueur"], "Category": 0}, {"Color": "tan", "ID": 92, "Name": "cranberry liqueur", "Brands": ["Cranberry liqueur", "Leopold Brothers New England Cranberry Liqueur", "Lapponia Polar Cranberry Liqueur", "Black Duck Cranberry Liqueur"], "Category": 0}, {"Color": "tan", "ID": 94, "Name": "elderberry liqueur", "Brands": ["Sambuca", "Elderberry liqueur", "Black Sambuca", "Opal Nera", "Blue sambuca"], "Category": 0}, {"Color": "tan", "ID": 99, "Name": "blueberry liqueur", "Brands": ["Blueberry liqueur", "Lapponia Blueberry Liqueur", "Weis Blueberry Liqueur", "Caselli Mirtillino Blueberry Liqueur"], "Category": 0}, {"Color": "tan", "ID": 103, "Name": "orange liqueur", "Brands": ["Blue Curacao", "Grand Marnier", "Cointreaux", "Green Curacao", "Orange Curacao", "Curacao", "White Curaco", "White Curacao", "Orange liqueur", "Bols Blue Curacao", "Red Curacao"], "Category": 0}, {"Color": "tan", "ID": 109, "Name": "yogurt liqueur", "Brands": ["Bols natural", "Yogurt liqueur"], "Category": 0}, {"Color": "tan", "ID": 112, "Name": "chocolate liqueur", "Brands": ["Creme de cacao", "Dark creme de cacao", "Light creme de cacao", "Chocolate liqueur", "White chocolate liquer", "Brown creme de cacao", "Godiva chocolate liqueur", "White creme de cacao"], "Category": 0}, {"Color": "tan", "ID": 130, "Name": "ginger liqueur", "Brands": ["SNAP ginger liqueur", "Ginger liqueur", "Canton Ginger Liqueur"], "Category": 0}, {"Color": "tan", "ID": 135, "Name": "caramel liqueur", "Brands": ["Caramel liqueur", "Godiva Caramel Liqueur"], "Category": 0}, {"Color": "tan", "ID": 152, "Name": "raspberry liqueur", "Brands": ["Chambord Raspberry Liqueur"], "Category": 0}, {"Color": "tan", "ID": 155, "Name": "Charleston Follies liqueur", "Brands": ["Charleston Follies"], "Category": 0}, {"Color": "tan", "ID": 160, "Name": "cherry liqueur", "Brands": ["Heering Cherry Liqueur", "Kirsch", "Kirschwasser", "Cherry liqueur", "Cherry Heering", "Cherry Marnier", "Maraschino liqueur"], "Category": 0}, {"Color": "tan", "ID": 168, "Name": "Mint liqueur", "Brands": ["Creme de menthe", "Mint liqueur", "Peppermint liquer", "Vandermint", "Chocolate mint liqueur"], "Category": 0}, {"Color": "tan", "ID": 194, "Name": "coffee liqueur", "Brands": ["Tia Maria", "Kahlua coffee liqueur", "Coffee liqueur"], "Category": 0}, {"Color": "tan", "ID": 213, "Name": "blackcurrant-flavored liqueur", "Brands": ["Creme de cassis"], "Category": 0}, {"Color": "tan", "ID": 235, "Name": "pineapple liqueur", "Brands": ["DeKuyper Tropical Pineapple Liqueur"], "Category": 0}, {"Color": "tan", "ID": 260, "Name": "Forbidden Fruit Liqueur", "Brands": ["Forbidden Fruit Liqueur"], "Category": 0}, {"Color": "tan", "ID": 267, "Name": "Fruit Liqueur", "Brands": ["Fruit Liqueur"], "Category": 0}, {"Color": "tan", "ID": 274, "Name": "Vanilla liqueur", "Brands": ["Galliano", "Tuaca", "Vanilla liqueur", "Liquer 43"], "Category": 0}, {"Color": "tan", "ID": 301, "Name": "Guavaberry Liqueur", "Brands": ["Guavaberry Liqueur"], "Category": 0}, {"Color": "tan", "ID": 313, "Name": "Herbal Liqueur", "Brands": ["Herbal Liqueur"], "Category": 0}, {"Color": "tan", "ID": 314, "Name": "Pumpkin Liqueur", "Brands": ["Pumpkin Spice Liqueur", "Skyy Pumpkin Infused Vodka", "Hiram Walker Pumpkin Spice Liqueur"], "Category": 0}, {"Color": "tan", "ID": 321, "Name": "Hpnotiq liqueur", "Brands": ["Hpnotiq liqueur"], "Category": 0}, {"Color": "tan", "ID": 337, "Name": "Kiwi Liqueur", "Brands": ["Kiwi Liqueur"], "Category": 0}, {"Color": "tan", "ID": 347, "Name": "La Grande Passion Liqueur", "Brands": ["La Grande Passion Liqueur"], "Category": 0}, {"Color": "tan", "ID": 348, "Name": "Lapponia Lakka Cloudberry Liqueur", "Brands": ["Lapponia Lakka Cloudberry Liqueur"], "Category": 0}, {"Color": "tan", "ID": 370, "Name": "Lime Citron Liqueur", "Brands": ["Lime Citron Liqueur"], "Category": 0}, {"Color": "tan", "ID": 376, "Name": "Lime Liqueur", "Brands": ["Lime Liqueur"], "Category": 0}, {"Color": "tan", "ID": 383, "Name": "lemon liqueur", "Brands": ["Limoncello"], "Category": 0}, {"Color": "tan", "ID": 390, "Name": "Lychee Liqueur", "Brands": ["Lychee Liqueur"], "Category": 0}, {"Color": "tan", "ID": 398, "Name": "Mandarin liqueur", "Brands": ["Mandarin liqueur"], "Category": 0}, {"Color": "tan", "ID": 402, "Name": "Mango Liqueur", "Brands": ["Mango Liqueur"], "Category": 0}, {"Color": "tan", "ID": 404, "Name": "Mango Passion Liqueur", "Brands": ["Mango Passion Liqueur"], "Category": 0}, {"Color": "tan", "ID": 418, "Name": "melon liqueur", "Brands": ["Melon liqueur", "Watermelon Liqueur", "Midori melon liqueur"], "Category": 0}, {"Color": "tan", "ID": 431, "Name": "Walnut Liqueur", "Brands": ["Nocello", "Walnut Liqueur"], "Category": 0}, {"Color": "tan", "ID": 460, "Name": "pomegranate liqueur", "Brands": ["PAMA pomegranate liqueur"], "Category": 0}, {"Color": "tan", "ID": 469, "Name": "Passion-fruit Liqueur", "Brands": ["Passion-fruit Liqueur"], "Category": 0}, {"Color": "tan", "ID": 478, "Name": "Peach Liqueur", "Brands": ["Peach Liqueur"], "Category": 0}, {"Color": "tan", "ID": 485, "Name": "Peanut Liqueur", "Brands": ["Peanut Liqueur"], "Category": 0}, {"Color": "tan", "ID": 489, "Name": "Pear Liqueur", "Brands": ["Pear Liqueur"], "Category": 0}, {"Color": "tan", "ID": 497, "Name": "Peppermint Liqueur", "Brands": ["Peppermint Liqueur"], "Category": 0}, {"Color": "tan", "ID": 504, "Name": "Pimento Liqueur", "Brands": ["Pimento Liqueur"], "Category": 0}, {"Color": "tan", "ID": 521, "Name": "Pistachio Liqueur", "Brands": ["Pistachio Liqueur"], "Category": 0}, {"Color": "tan", "ID": 523, "Name": "Plum Liqueur", "Brands": ["Prunelle", "Plum Liqueur"], "Category": 0}, {"Color": "tan", "ID": 526, "Name": "Poire Williams Liqueur", "Brands": ["Poire Williams Liqueur"], "Category": 0}, {"Color": "tan", "ID": 539, "Name": "Raki Liqueur", "Brands": ["Raki Liqueur"], "Category": 0}, {"Color": "tan", "ID": 565, "Name": "Safari Liqueur", "Brands": ["Safari Liqueur"], "Category": 0}, {"Color": "tan", "ID": 566, "Name": "tomato liqueur", "Brands": ["Sakura Muro Machi Tomato Liqueur", "Tomato liqueur"], "Category": 0}, {"Color": "tan", "ID": 591, "Name": "peach liqueur", "Brands": ["Southern Comfort"], "Category": 0}, {"Color": "tan", "ID": 599, "Name": "St. Hallvard Liqueur", "Brands": ["St. Hallvard Liqueur"], "Category": 0}, {"Color": "tan", "ID": 608, "Name": "Strawberry liqueur", "Brands": ["Strawberry liqueur"], "Category": 0}, {"Color": "tan", "ID": 634, "Name": "Tropical Blue liqueur", "Brands": ["Tropical Blue liqueur"], "Category": 0}, {"Color": "tan", "ID": 668, "Name": "Wild Spirit Liqueur", "Brands": ["Wild Spirit Liqueur"], "Category": 0}, {"Color": "tan", "ID": 1, "Name": "apple schnapps", "Brands": ["Apple schnapps", "Apple Pucker sour apple schnapps", "Dekuyper Sour Apple Pucker", "99 apples schnapps", "DeKuyper Sour Apple Pucker Schnapps"], "Category": 0}, {"Color": "tan", "ID": 47, "Name": "appricot schnapps", "Brands": ["Apricot schnapps"], "Category": 0}, {"Color": "tan", "ID": 48, "Name": "peach schnapps", "Brands": ["Archer's peach schnapps", "Peach schnapps"], "Category": 0}, {"Color": "tan", "ID": 66, "Name": "banana schnapps", "Brands": ["Banana schnapps"], "Category": 0}, {"Color": "tan", "ID": 86, "Name": "blackberry schnapps", "Brands": ["Blackberry schnapps", "Black haus"], "Category": 0}, {"Color": "tan", "ID": 100, "Name": "blueberry schnapps", "Brands": ["Blueberry schnapps"], "Category": 0}, {"Color": "tan", "ID": 110, "Name": "rootbeer schnapps", "Brands": ["Bols rootbeer schnapps"], "Category": 0}, {"Color": "tan", "ID": 124, "Name": "cactus juice schnapps", "Brands": ["Cactus juice schnapps"], "Category": 0}, {"Color": "tan", "ID": 176, "Name": "cinnamon schnapps", "Brands": ["Cinnamon schnapps", "Goldschlager"], "Category": 0}, {"Color": "tan", "ID": 209, "Name": "Cranberry Schnapps", "Brands": ["Cranberry Schnapps"], "Category": 0}, {"Color": "tan", "ID": 291, "Name": "Grape Schnapps", "Brands": ["Grape Schnapps"], "Category": 0}, {"Color": "tan", "ID": 360, "Name": "Lemon Schnapps", "Brands": ["Lemon Schnapps"], "Category": 0}, {"Color": "tan", "ID": 415, "Name": "Maui Blue Hawaiian Schnapps", "Brands": ["Maui Blue Hawaiian Schnapps"], "Category": 0}, {"Color": "tan", "ID": 419, "Name": "Melon Schnapps", "Brands": ["Melon Schnapps"], "Category": 0}, {"Color": "tan", "ID": 421, "Name": "Mentholmint Schnapps", "Brands": ["Mentholmint Schnapps"], "Category": 0}, {"Color": "tan", "ID": 427, "Name": "Mint Schnapps", "Brands": ["Mint Schnapps"], "Category": 0}, {"Color": "tan", "ID": 491, "Name": "Pear Schnapps", "Brands": ["Pear Schnapps"], "Category": 0}, {"Color": "tan", "ID": 498, "Name": "peppermint schnapps", "Brands": ["Peppermint schnapps", "Rumpleminz"], "Category": 0}, {"Color": "tan", "ID": 508, "Name": "Pina Colada Schnapps", "Brands": ["Pina Colada Schnapps"], "Category": 0}, {"Color": "tan", "ID": 545, "Name": "Raspberry Schnapps", "Brands": ["Raspberry Schnapps"], "Category": 0}, {"Color": "tan", "ID": 610, "Name": "Strawberry Schnapps", "Brands": ["Strawberry Schnapps"], "Category": 0}, {"Color": "tan", "ID": 629, "Name": "Tangerine Schnapps", "Brands": ["Tangerine Schnapps"], "Category": 0}, {"Color": "tan", "ID": 636, "Name": "Tropical Fruit Schnapps", "Brands": ["Tropical-fruit Schnapps", "Tropical Fruit Schnapps"], "Category": 0}, {"Color": "tan", "ID": 647, "Name": "Vanilla Schnapps", "Brands": ["Vanilla Schnapps"], "Category": 0}, {"Color": "tan", "ID": 658, "Name": "Watermelon Schnapps", "Brands": ["Watermelon Schnapps"], "Category": 0}, {"Color": "tan", "ID": 666, "Name": "Wildberry Schnapps", "Brands": ["Wildberry Schnapps"], "Category": 0}, {"Color": "tan", "ID": 676, "Name": "Yukon Jack Perma Frost Schnapps", "Brands": ["Yukon Jack Perma Frost Schnapps"], "Category": 0}, {"Color": "tan", "ID": 25, "Name": "Amaro", "Brands": ["Luxardo Amaro Abano", "Amaro Montenegro"], "Category": 0}, {"Color": "tan", "ID": 141, "Name": "cardamaro", "Brands": ["Cardamaro"], "Category": 0}, {"Color": "tan", "ID": 27, "Name": "Amer Picon aperitif", "Brands": ["Amer Picon"], "Category": 0}, {"Color": "tan", "ID": 156, "Name": "chartreuse", "Brands": ["Chartreuse"], "Category": 0}, {"Color": "tan", "ID": 364, "Name": "Licor 43", "Brands": ["Licor 43"], "Category": 0}, {"Color": "light blue", "ID": 76, "Name": "Gin", "Brands": ["Hendrick's Gin", "Bombay Gin", "Bombay Sapphire gin", "Sloe gin", "Sapphire gin", "Beefeater gin", "Lemon gin", "Tanqueray gin", "Gordons Gin", "Bellringer Gin", "DeKuyper Sloe Gin", "Gin", "Dry gin"], "Category": 0}, {"Color": "light blue", "ID": 222, "Name": "ginger", "Brands": ["Crystallized ginger", "Ginger simple syrup", "Freshly grated ginger", "Ginger"], "Category": 0}, {"Color": "yellow", "ID": 277, "Name": "Ginger ale", "Brands": ["Gingerale", "Ginger ale"], "Category": 0}, {"Color": "yellow", "ID": 278, "Name": "Ginger beer", "Brands": ["Ginger beer"], "Category": 0}, {"Color": "brown", "ID": 279, "Name": "Ginger Brandy", "Brands": ["Ginger Brandy"], "Category": 0}, {"Color": "light blue", "ID": 280, "Name": "Ginger Syrup", "Brands": ["Ginger syrup"], "Category": 0}, {"Color": "purple", "ID": 281, "Name": "Ginger Wine", "Brands": ["Ginger Wine"], "Category": 0}, {"Color": "purple", "ID": 297, "Name": "Green Ginger Wine", "Brands": ["Green Ginger Wine"], "Category": 0}, {"Color": "light blue", "ID": 371, "Name": "Lime Gin", "Brands": ["Lime Gin"], "Category": 0}, {"Color": "light blue", "ID": 425, "Name": "Mint Gin", "Brands": ["Mint Gin"], "Category": 0}, {"Color": "light blue", "ID": 446, "Name": "Orange Gin", "Brands": ["Orange Gin"], "Category": 0}, {"Color": "light blue", "ID": 457, "Name": "Orangina", "Brands": ["Orangina"], "Category": 0}, {"Color": "light blue", "ID": 4, "Name": "citrus-infused vodka", "Brands": ["Burnett's citrus vodka", "Burnett's orange vodka", "Lemon vodka", "Grey Goose L'orange Vodka", "Absolut Citron", "Stoli Orahnj vodka", "Stoli orange", "Finlandia lime vodka"], "Category": 0}, {"Color": "light blue", "ID": 5, "Name": "cranberry vodka", "Brands": ["Absolut cranberry", "Finlandia Cranberry vodka"], "Category": 0}, {"Color": "light blue", "ID": 6, "Name": "currant-infused vodka", "Brands": ["Absolut Kurant", "Absolut Kurant vodka"], "Category": 0}, {"Color": "light blue", "ID": 7, "Name": "mandarin vodka", "Brands": ["Mandarin vodka", "Mandarin-flavored vodka", "Absolut Mandarin"], "Category": 0}, {"Color": "light blue", "ID": 8, "Name": "pepper vodka", "Brands": ["Absolut Peppar", "Stolichnaya Pertsovka Pepper Vodka", "Pepper Vodka"], "Category": 0}, {"Color": "light blue", "ID": 9, "Name": "vanilla vodka", "Brands": ["Burnett's vanilla vodka", "Stoli Vanilla", "Absolut Vanilia vodka", "Seagram's Vanilla Vodka"], "Category": 0}, {"Color": "light blue", "ID": 10, "Name": "Vodka", "Brands": ["Blavod vodka", "Ciroc vodka", "Japanese whiskey", "Smirnoff vodka", "Wyborowa vodka", "Stoli vodka", "Three Olives vodka", "Stoli kafya", "Vox vodka", "Absolut vodka", "Stolichnaya vodka", "Tanqueray Sterling vodka", "Grey Goose vodka", "Cytronowka vodka", "Mati Hari Ladies Vodka", "Pearl vodka", "Red vodka", "Ursus vodka", "Stolichnaya Gold vodka", "Ketel One Vodka"], "Category": 0}, {"Color": "light blue", "ID": 42, "Name": "apple vodka", "Brands": ["Burnett's sour apple vodka", "Apple vodka"], "Category": 0}, {"Color": "light blue", "ID": 102, "Name": "blueberry vodka", "Brands": ["Blueberry vodka"], "Category": 0}, {"Color": "light blue", "ID": 114, "Name": "cherry vodka", "Brands": ["UV Red Cherry Vodka", "Burnett's Cherry Vodka", "Three Olives Cherry Vodka", "Cherry vodka"], "Category": 0}, {"Color": "light blue", "ID": 115, "Name": "Coconut Vodka", "Brands": ["Burnett's coconut vodka"], "Category": 0}, {"Color": "light blue", "ID": 116, "Name": "berry-infused vodka", "Brands": ["Stoli Strawberry vodka", "Stoli Raspberry vodka", "Burnett's raspberry vodka", "Gordon's Wildberry vodka"], "Category": 0}, {"Color": "light blue", "ID": 138, "Name": "caramel vodka", "Brands": ["Caramel Vodka", "Smirnoff Kissed Caramel"], "Category": 0}, {"Color": "light blue", "ID": 172, "Name": "chocolate vodka", "Brands": ["Chocolate vodka", "Three Olives Chocolate Vodka", "Vincent Van Gogh Chocolate Vodka"], "Category": 0}, {"Color": "light blue", "ID": 173, "Name": "potato vodka", "Brands": ["Potato vodka", "Chopin vodka"], "Category": 0}, {"Color": "light blue", "ID": 178, "Name": "cinnamon vodka", "Brands": ["Cinnamon vodka"], "Category": 0}, {"Color": "light blue", "ID": 195, "Name": "coffee vodka", "Brands": ["Vincent Van Gogh Double Espresso Vodka", "Pinnacle Vodka Coffee Flavor", "Coffee vodka", "Three Olives Triple Shot Espresso Vodka"], "Category": 0}, {"Color": "light blue", "ID": 210, "Name": "Cranberry Vodka", "Brands": ["Cranberry Vodka"], "Category": 0}, {"Color": "light blue", "ID": 227, "Name": "Current Vodka", "Brands": ["Current Vodka"], "Category": 0}, {"Color": "light blue", "ID": 255, "Name": "sweet tea vodka", "Brands": ["Sweet tea vodka", "Firefly Sweet Tea Flavored Vodka"], "Category": 0}, {"Color": "light blue", "ID": 318, "Name": "Honey Vodka", "Brands": ["Honey Vodka"], "Category": 0}, {"Color": "light blue", "ID": 382, "Name": "Lime Vodka", "Brands": ["Lime Vodka"], "Category": 0}, {"Color": "light blue", "ID": 420, "Name": "Melon Vodka", "Brands": ["Melon Vodka"], "Category": 0}, {"Color": "light blue", "ID": 455, "Name": "Orange Vodka", "Brands": ["Orange Vodka"], "Category": 0}, {"Color": "light blue", "ID": 483, "Name": "Peach Vodka", "Brands": ["Peach Vodka"], "Category": 0}, {"Color": "light blue", "ID": 514, "Name": "pineapple vodka", "Brands": ["Pineapple vodka"], "Category": 0}, {"Color": "light blue", "ID": 517, "Name": "Marshmallow Vodka", "Brands": ["Smirnoff Fluffed Marshmallow Vodka", "Pinnacle Marshmallow Vodka"], "Category": 0}, {"Color": "light blue", "ID": 518, "Name": "whipped cream vodka", "Brands": ["Pinnacle Whipped"], "Category": 0}, {"Color": "light blue", "ID": 530, "Name": "Pravda Vodka", "Brands": ["Pravda Vodka"], "Category": 0}, {"Color": "light blue", "ID": 533, "Name": "pumpkin vodka", "Brands": ["Pumpkin Pie Vodka"], "Category": 0}, {"Color": "light blue", "ID": 549, "Name": "Raspberry Vodka", "Brands": ["Raspberry Vodka"], "Category": 0}, {"Color": "light blue", "ID": 579, "Name": "Clove-infused vodka", "Brands": ["Skyy Cinnamon Clove Infused Vodka"], "Category": 0}, {"Color": "light blue", "ID": 582, "Name": "Smirnoff Orange Twist Vodka", "Brands": ["Smirnoff Orange Twist Vodka"], "Category": 0}, {"Color": "light blue", "ID": 583, "Name": "Smirnoff Raspberry Twist Vodka", "Brands": ["Smirnoff Raspberry Twist Vodka"], "Category": 0}, {"Color": "light blue", "ID": 584, "Name": "Smirnoff Vanilla Twist Vodka", "Brands": ["Smirnoff Vanilla Twist Vodka"], "Category": 0}, {"Color": "light blue", "ID": 596, "Name": "Spiced vodka", "Brands": ["Spiced vodka"], "Category": 0}, {"Color": "light blue", "ID": 613, "Name": "Strawberry Vodka", "Brands": ["Strawberry Vodka"], "Category": 0}, {"Color": "light blue", "ID": 641, "Name": "Van Gogh Vodka", "Brands": ["Van Gogh Vodka"], "Category": 0}, {"Color": "light blue", "ID": 659, "Name": "Watermelon Vodka", "Brands": ["Watermelon Vodka"], "Category": 0}, {"Color": "light blue", "ID": 667, "Name": "Wildberry Vodka", "Brands": ["Wildberry Vodka"], "Category": 0}, {"Color": "light blue", "ID": 330, "Name": "jenever", "Brands": ["Jenever"], "Category": 0}, {"Color": "purple", "ID": 121, "Name": "Byrrh Wine", "Brands": ["Byrrh Wine"], "Category": 0}, {"Color": "purple", "ID": 122, "Name": "red wine", "Brands": ["Cabernet Sauvignon", "Red wine"], "Category": 0}, {"Color": "purple", "ID": 154, "Name": "white wine", "Brands": ["Sauvignon blanc", "White wine", "Chardonnay"], "Category": 0}, {"Color": "purple", "ID": 391, "Name": "Lychee Wine", "Brands": ["Lychee Wine"], "Category": 0}, {"Color": "purple", "ID": 394, "Name": "fortified wine", "Brands": ["Sherry", "Madeira"], "Category": 0}, {"Color": "purple", "ID": 515, "Name": "Pineapple Wine", "Brands": ["Pineapple Wine"], "Category": 0}, {"Color": "purple", "ID": 525, "Name": "Plum Wine", "Brands": ["Plum Wine"], "Category": 0}, {"Color": "purple", "ID": 556, "Name": "Red Sparkling Wine", "Brands": ["Red Sparkling Wine"], "Category": 0}, {"Color": "purple", "ID": 254, "Name": "fino sherry", "Brands": ["Fino sherry", "Manzanilla sherry"], "Category": 0}, {"Color": "purple", "ID": 367, "Name": "Lillet", "Brands": ["Lillet Rose", "Lillet"], "Category": 0}, {"Color": "purple", "ID": 393, "Name": "Mad Dog", "Brands": ["Mad Dog"], "Category": 0}, {"Color": "brown", "ID": 43, "Name": "Apricot Brandy", "Brands": ["Apricot Brandy", "De Kuyper Apricot Brandy"], "Category": 0}, {"Color": "brown", "ID": 84, "Name": "Blackberry Brandy", "Brands": ["Blackberry Brandy"], "Category": 0}, {"Color": "brown", "ID": 111, "Name": "Brandy", "Brands": ["Brandy", "California brandy"], "Category": 0}, {"Color": "brown", "ID": 158, "Name": "Cherry brandy", "Brands": ["Cherry brandy", "Cherry Heering brandy"], "Category": 0}, {"Color": "brown", "ID": 192, "Name": "coffee brandy", "Brands": ["Coffee brandy"], "Category": 0}, {"Color": "brown", "ID": 293, "Name": "Pomace Brandy", "Brands": ["Grappa"], "Category": 0}, {"Color": "brown", "ID": 444, "Name": "Orange Brandy", "Brands": ["Orange Brandy"], "Category": 0}, {"Color": "brown", "ID": 476, "Name": "peach brandy", "Brands": ["Peach brandy"], "Category": 0}, {"Color": "brown", "ID": 487, "Name": "Pear Brandy", "Brands": ["Pear Brandy"], "Category": 0}, {"Color": "brown", "ID": 522, "Name": "Plum Brandy", "Brands": ["Plum Brandy"], "Category": 0}, {"Color": "brown", "ID": 593, "Name": "Spanish Brandy", "Brands": ["Spanish Brandy"], "Category": 0}, {"Color": "brown", "ID": 602, "Name": "Strawberry Brandy", "Brands": ["Strawberry Brandy"], "Category": 0}, {"Color": "brown", "ID": 78, "Name": "beer", "Brands": ["Lager beer", "Beer", "Budweiser beer"], "Category": 0}, {"Color": "brown", "ID": 170, "Name": "chocolate beer", "Brands": ["Chocolate stout beer"], "Category": 0}, {"Color": "brown", "ID": 202, "Name": "light beer", "Brands": ["Light beer", "Hoegaarden beer", "Corona"], "Category": 0}, {"Color": "brown", "ID": 305, "Name": "dark beer", "Brands": ["Guinness stout", "Guinness", "Porter"], "Category": 0}, {"Color": "brown", "ID": 324, "Name": "IPA beer", "Brands": ["IPA beer"], "Category": 0}, {"Color": "light blue", "ID": 123, "Name": "Cachaca", "Brands": ["Cachaca"], "Category": 0}, {"Color": "light blue", "ID": 519, "Name": "pisco", "Brands": ["Pisco"], "Category": 0}, {"Color": "purple", "ID": 252, "Name": "Fernet Branca", "Brands": ["Fernet", "Fernet Branca"], "Category": 0}, {"Color": "tan", "ID": 15, "Name": "Aquavit", "Brands": ["Aquavit", "Akvavit"], "Category": 0}, {"Color": "yellow", "ID": 108, "Name": "Champagne", "Brands": ["Rose Brut Champagne", "Sparkling Moscato", "Sparkling Rose", "Blush wine", "Champagne", "Sparkling wine", "Rose", "Prosecco"], "Category": 0}, {"Color": "brown", "ID": 49, "Name": "arrack", "Brands": ["Arrack"], "Category": 0}, {"Color": "light blue", "ID": 576, "Name": "Shochu", "Brands": ["Shochu"], "Category": 0}, {"Color": "light blue", "ID": 253, "Name": "Sake", "Brands": ["Gekkeikan", "Filtered sake", "Sake"], "Category": 0}, {"Color": "light blue", "ID": 224, "Name": "Tequila", "Brands": ["Patron Reposado", "Cuervo Gold tequila", "Jose Cuervo Gold tequila", "Riserva 100% Anejo tequila", "Jose Cuervo tequila", "White Tequila", "Sauza Commemorativo Tequila", "Tequila Rose", "Sauza Extra Gold Tequila", "Gold Tequila", "Cuervo tequila", "Sauza Hornitos tequila", "Sauza tequila", "Sauza Blanco", "Tequila blanco", "Tres generations tequila", "Silver tequila", "Que Pentas silver tequila", "Sauza Tres Generations Tequila", "Patron silver tequila"], "Category": 0}, {"Color": "light blue", "ID": 474, "Name": "spicy tequila", "Brands": ["Patron Incendio"], "Category": 0}, {"Color": "light blue", "ID": 424, "Name": "Mezcal", "Brands": ["Mezcal"], "Category": 0}, {"Color": "purple", "ID": 350, "Name": "LBV Port", "Brands": ["LBV Port"], "Category": 0}, {"Color": "purple", "ID": 529, "Name": "port", "Brands": ["Tawny port", "Port", "Ruby port"], "Category": 0}, {"Color": "purple", "ID": 665, "Name": "White Port", "Brands": ["White Port"], "Category": 0}, {"Color": "brown", "ID": 256, "Name": "Firewater", "Brands": ["Firewater"], "Category": 0}, {"Color": "green", "ID": 3, "Name": "absinthe", "Brands": ["Absinthe", "Versinthe", "Pernod", "Herbsaint"], "Category": 0}, {"Color": "brown", "ID": 396, "Name": "Mandarine Napoleon", "Brands": ["Mandarine Napoleon"], "Category": 0}, {"Color": "red", "ID": 239, "Name": "Hard Cider", "Brands": ["Dry hard cider", "Hard Cider"], "Category": 0}, {"Color": "red", "ID": 159, "Name": "cherry cider", "Brands": ["Cherry cider"], "Category": 0}, {"Color": "red", "ID": 616, "Name": "Strongbow Cider", "Brands": ["Strongbow Cider"], "Category": 0}, {"Color": "brown", "ID": 325, "Name": "Irish Mist", "Brands": ["Irish Mist"], "Category": 0}, {"Color": "yellow", "ID": 310, "Name": "Hard Lemonade", "Brands": ["Hard Lemonade"], "Category": 0}, {"Color": "tan", "ID": 677, "Name": "Zima", "Brands": ["Zima"], "Category": 0}, {"Color": "brown", "ID": 625, "Name": "Taboo", "Brands": ["Taboo"], "Category": 0}, {"Color": "tan", "ID": 180, "Name": "orange-flavored vermouth", "Brands": ["Orange-flavored vermouth", "Cinzano Orancio"], "Category": 0}, {"Color": "tan", "ID": 241, "Name": "dry vermouth", "Brands": ["Dry vermouth", "French dry vermouth", "Noily Prat dry vermouth", "Martini & Rossi extra dry vermouth"], "Category": 0}, {"Color": "tan", "ID": 326, "Name": "sweet vermouth", "Brands": ["Noilly Prat Ambre vermouth", "Sweet vermouth", "Italian sweet vermouth"], "Category": 0}, {"Color": "dark brown", "ID": 327, "Name": "Jagermeister", "Brands": ["Jagermeister"], "Category": 0}, {"Color": "dark red", "ID": 56, "Name": "orange soda", "Brands": ["Bacardi Breezer Orange", "Orange soda", "Cactus Cooler Orange-Pineapple Soda"], "Category": 1}, {"Color": "dark red", "ID": 126, "Name": "cranberry soda", "Brands": ["Canada dry cranberry soda"], "Category": 1}, {"Color": "dark red", "ID": 153, "Name": "Champagne Soda ", "Brands": ["Champagne Soda"], "Category": 1}, {"Color": "dark red", "ID": 185, "Name": "clear soda", "Brands": ["Lemon lime soda", "Soda water", "Club soda"], "Category": 1}, {"Color": "dark red", "ID": 212, "Name": "Cream Soda", "Brands": ["Cream Soda"], "Category": 1}, {"Color": "dark red", "ID": 270, "Name": "Fruit Soda", "Brands": ["Fruit Soda"], "Category": 1}, {"Color": "dark red", "ID": 287, "Name": "Grapefruit Soda", "Brands": ["Grapefruit Soda"], "Category": 1}, {"Color": "dark red", "ID": 292, "Name": "Grape Soda", "Brands": ["Grape Soda"], "Category": 1}, {"Color": "dark red", "ID": 358, "Name": "Lemon-Lime Soda", "Brands": ["Lemon-Lime Soda"], "Category": 1}, {"Color": "dark red", "ID": 362, "Name": "Lemon Soda", "Brands": ["Lemon Soda"], "Category": 1}, {"Color": "dark red", "ID": 380, "Name": "Lime Soda", "Brands": ["Lime Soda"], "Category": 1}, {"Color": "dark red", "ID": 406, "Name": "Mango Soda", "Brands": ["Mango Soda"], "Category": 1}, {"Color": "dark red", "ID": 492, "Name": "Pear Soda", "Brands": ["Pear Soda"], "Category": 1}, {"Color": "dark red", "ID": 512, "Name": "Pineapple Soda", "Brands": ["Pineapple Soda"], "Category": 1}, {"Color": "dark red", "ID": 547, "Name": "Raspberry Soda", "Brands": ["Raspberry Soda"], "Category": 1}, {"Color": "dark red", "ID": 555, "Name": "Red Soda", "Brands": ["Red Soda"], "Category": 1}, {"Color": "dark red", "ID": 611, "Name": "Strawberry Soda", "Brands": ["Strawberry Soda"], "Category": 1}, {"Color": "dark red", "ID": 626, "Name": "Tahitian Treat Soda", "Brands": ["Tahitian Treat Soda"], "Category": 1}, {"Color": "dark red", "ID": 186, "Name": "coke", "Brands": ["Coke", "Pepsi", "Diet Coke", "Diet Pepsi", "Cola", "Coca-Cola"], "Category": 1}, {"Color": "dark red", "ID": 196, "Name": "coke syrup", "Brands": ["Coke syrup"], "Category": 1}, {"Color": "dark red", "ID": 644, "Name": "Vanilla Coke", "Brands": ["Vanilla Coke"], "Category": 1}, {"Color": "dark red", "ID": 299, "Name": "Grenadine", "Brands": ["Grenadine", "Grenadine syrup"], "Category": 1}, {"Color": "red", "ID": 106, "Name": "Berry Kool-Aid", "Brands": ["Blue Moon Berry Kool-Aid", "Blue Raspberry Kool-Aid"], "Category": 1}, {"Color": "red", "ID": 289, "Name": "Grape Kool-Aid", "Brands": ["Grape Kool-Aid"], "Category": 1}, {"Color": "red", "ID": 343, "Name": "Kool Aid", "Brands": ["Kool Aid"], "Category": 1}, {"Color": "red", "ID": 357, "Name": "Lemon-Lime Kool-Aid", "Brands": ["Lemon-Lime Kool-Aid"], "Category": 1}, {"Color": "red", "ID": 375, "Name": "Lime Kool-Aid", "Brands": ["Lime Kool-Aid"], "Category": 1}, {"Color": "red", "ID": 401, "Name": "Mango Kool-Aid", "Brands": ["Mango Kool-Aid"], "Category": 1}, {"Color": "red", "ID": 450, "Name": "Orange Kool-Aid", "Brands": ["Orange Kool-Aid"], "Category": 1}, {"Color": "red", "ID": 607, "Name": "Strawberry Kool-Aid", "Brands": ["Strawberry Kool-Aid"], "Category": 1}, {"Color": "red", "ID": 628, "Name": "Tangerine Kool-aid", "Brands": ["Tangerine Kool-aid"], "Category": 1}, {"Color": "red", "ID": 637, "Name": "Tropical Punch Kool-Aid", "Brands": ["Tropical Punch Kool-Aid"], "Category": 1}, {"Color": "red", "ID": 655, "Name": "Watermelon-Cherry Kool-Aid", "Brands": ["Watermelon-Cherry Kool-Aid"], "Category": 1}, {"Color": "purple", "ID": 40, "Name": "apple juice", "Brands": ["Apple juice", "Apple sauce"], "Category": 1}, {"Color": "purple", "ID": 45, "Name": "apricot juice", "Brands": ["Apricot juice"], "Category": 1}, {"Color": "purple", "ID": 90, "Name": "black currant juice", "Brands": ["Blackcurrant juice"], "Category": 1}, {"Color": "purple", "ID": 95, "Name": "blood orange juice", "Brands": ["Blood orange juice"], "Category": 1}, {"Color": "purple", "ID": 96, "Name": "tomato juice", "Brands": ["Tomato juice", "V8", "Bloody mary mix"], "Category": 1}, {"Color": "purple", "ID": 98, "Name": "blueberry juice", "Brands": ["Blueberry juice"], "Category": 1}, {"Color": "purple", "ID": 107, "Name": "blue raspberry juice", "Brands": ["Blue raspberry juice"], "Category": 1}, {"Color": "purple", "ID": 146, "Name": "carrot juice", "Brands": ["Carrot juice"], "Category": 1}, {"Color": "purple", "ID": 147, "Name": "cashew fruit juice", "Brands": ["Cashew fruit juice"], "Category": 1}, {"Color": "purple", "ID": 182, "Name": "clam juice", "Brands": ["Clam juice", "Clamato Juice"], "Category": 1}, {"Color": "purple", "ID": 207, "Name": "Cranberry Juice", "Brands": ["Cranberry Juice", "Cranapple juice", "Cranberry-raspberry juice"], "Category": 1}, {"Color": "purple", "ID": 266, "Name": "Fruit Juice", "Brands": ["Fruit Juice"], "Category": 1}, {"Color": "purple", "ID": 271, "Name": "Fruits of the Forest Juice", "Brands": ["Fruits of the Forest Juice"], "Category": 1}, {"Color": "purple", "ID": 286, "Name": "grapefruit juice", "Brands": ["Grapefruit juice"], "Category": 1}, {"Color": "purple", "ID": 288, "Name": "grape juice", "Brands": ["Grape Juice"], "Category": 1}, {"Color": "purple", "ID": 302, "Name": "guava juice", "Brands": ["Guava juice"], "Category": 1}, {"Color": "purple", "ID": 336, "Name": "Kiwi Juice", "Brands": ["Kiwi Juice"], "Category": 1}, {"Color": "purple", "ID": 339, "Name": "Kiwi-Strawberry Juice", "Brands": ["Kiwi-Strawberry Juice"], "Category": 1}, {"Color": "purple", "ID": 356, "Name": "Lemon Juice", "Brands": ["Lemon Juice"], "Category": 1}, {"Color": "purple", "ID": 374, "Name": "Lime Juice", "Brands": ["Lime Juice"], "Category": 1}, {"Color": "purple", "ID": 389, "Name": "Lychee Juice", "Brands": ["Lychee Juice"], "Category": 1}, {"Color": "purple", "ID": 397, "Name": "Mandarin Juice", "Brands": ["Mandarin Juice"], "Category": 1}, {"Color": "purple", "ID": 400, "Name": "Mango juice", "Brands": ["Mango juice"], "Category": 1}, {"Color": "purple", "ID": 409, "Name": "Maracuja Juice", "Brands": ["Maracuja Juice"], "Category": 1}, {"Color": "purple", "ID": 438, "Name": "Olive Juice", "Brands": ["Olive Juice"], "Category": 1}, {"Color": "purple", "ID": 449, "Name": "Orange Juice", "Brands": ["Orange Juice"], "Category": 1}, {"Color": "purple", "ID": 462, "Name": "Papaya Juice", "Brands": ["Papaya Juice"], "Category": 1}, {"Color": "purple", "ID": 467, "Name": "Passionfruit Juice", "Brands": ["Passionfruit juice"], "Category": 1}, {"Color": "purple", "ID": 468, "Name": "Passion-fruit Juice", "Brands": ["Passion-fruit Juice"], "Category": 1}, {"Color": "purple", "ID": 488, "Name": "Pear Juice", "Brands": ["Pear Juice"], "Category": 1}, {"Color": "purple", "ID": 503, "Name": "Pickle Juice", "Brands": ["Pickle Juice"], "Category": 1}, {"Color": "purple", "ID": 506, "Name": "Pimp Juice", "Brands": ["Pimp Juice"], "Category": 1}, {"Color": "purple", "ID": 510, "Name": "Pineapple Juice", "Brands": ["Pineapple Juice"], "Category": 1}, {"Color": "purple", "ID": 516, "Name": "Pine-Orange-Banana Juice", "Brands": ["Pine-Orange-Banana Juice"], "Category": 1}, {"Color": "purple", "ID": 527, "Name": "Pomegranate Juice", "Brands": ["Pomegranate Juice"], "Category": 1}, {"Color": "purple", "ID": 531, "Name": "Prune Juice", "Brands": ["Prune Juice"], "Category": 1}, {"Color": "purple", "ID": 543, "Name": "Raspberry Juice", "Brands": ["Raspberry Juice"], "Category": 1}, {"Color": "purple", "ID": 594, "Name": "Sparkling Apple Juice", "Brands": ["Sparkling Apple Juice"], "Category": 1}, {"Color": "purple", "ID": 597, "Name": "Spicy Hot Vegetable Juice", "Brands": ["Spicy Hot Vegetable Juice"], "Category": 1}, {"Color": "purple", "ID": 604, "Name": "Strawberry Guava Juice", "Brands": ["Strawberry Guava Juice"], "Category": 1}, {"Color": "purple", "ID": 620, "Name": "Sweetened Lime Juice", "Brands": ["Sweetened Lime Juice"], "Category": 1}, {"Color": "purple", "ID": 651, "Name": "Vegetable Juice", "Brands": ["Vegetable Juice"], "Category": 1}, {"Color": "purple", "ID": 653, "Name": "VSplash Fruit Juice", "Brands": ["VSplash Fruit Juice"], "Category": 1}, {"Color": "purple", "ID": 662, "Name": "White Cranberry & Strawberry Juice", "Brands": ["White Cranberry & Strawberry Juice"], "Category": 1}, {"Color": "yellow", "ID": 70, "Name": "sweet & sour mix", "Brands": ["Sweet & sour mix", "Bar mix", "Sour mix"], "Category": 1}, {"Color": "yellow", "ID": 197, "Name": "collins mix", "Brands": ["Collins mix"], "Category": 1}, {"Color": "yellow", "ID": 225, "Name": "Margarita Mix", "Brands": ["Margarita mix", "Cuervo Margarita mix"], "Category": 1}, {"Color": "yellow", "ID": 229, "Name": "Daiquiri Mix", "Brands": ["Daiquiri Mix"], "Category": 1}, {"Color": "yellow", "ID": 353, "Name": "Lemonade Mix", "Brands": ["Lemonade Mix"], "Category": 1}, {"Color": "yellow", "ID": 377, "Name": "Lime Mix", "Brands": ["Lime Mix"], "Category": 1}, {"Color": "yellow", "ID": 385, "Name": "Long Island Iced Tea Mix", "Brands": ["Long Island Iced Tea Mix"], "Category": 1}, {"Color": "yellow", "ID": 534, "Name": "pumpkin pudding mix", "Brands": ["Pumpkin pudding mix"], "Category": 1}, {"Color": "yellow", "ID": 603, "Name": "Strawberry Daiquiri Mix", "Brands": ["Strawberry Daiquiri Mix"], "Category": 1}, {"Color": "yellow", "ID": 609, "Name": "Strawberry Margarita Mix", "Brands": ["Strawberry Margarita Mix"], "Category": 1}, {"Color": "white", "ID": 167, "Name": "milk", "Brands": ["Chocolate milk", "Steamed milk", "Cream", "Milk"], "Category": 1}, {"Color": "white", "ID": 190, "Name": "coconut milk", "Brands": ["Coconut water", "Coconut milk"], "Category": 1}, {"Color": "white", "ID": 249, "Name": "Evaporated Milk", "Brands": ["Evaporated Milk"], "Category": 1}, {"Color": "white", "ID": 395, "Name": "Malted Milk", "Brands": ["Malted Milk"], "Category": 1}, {"Color": "white", "ID": 308, "Name": "half and half", "Brands": ["Half and half"], "Category": 1}, {"Color": "orange", "ID": 303, "Name": "Guava Nectar", "Brands": ["Guava Nectar"], "Category": 1}, {"Color": "orange", "ID": 386, "Name": "Looza mango nectar", "Brands": ["Looza mango nectar"], "Category": 1}, {"Color": "orange", "ID": 403, "Name": "Mango Nectar", "Brands": ["Mango Nectar"], "Category": 1}, {"Color": "orange", "ID": 463, "Name": "Papaya Nectar", "Brands": ["Papaya Nectar"], "Category": 1}, {"Color": "orange", "ID": 479, "Name": "Peach Nectar", "Brands": ["Peach Nectar"], "Category": 1}, {"Color": "orange", "ID": 490, "Name": "pear nectar", "Brands": ["Pear puree", "Pear nectar"], "Category": 1}, {"Color": "white", "ID": 312, "Name": "heavy cream", "Brands": ["Sweet cream", "Heavy cream"], "Category": 1}, {"Color": "white", "ID": 365, "Name": "Light Cream", "Brands": ["Light Cream"], "Category": 1}, {"Color": "creamy brown", "ID": 165, "Name": "hot chocolate", "Brands": ["Hot chocolate", "Chocolate", "Cocoa", "Hot cocoa"], "Category": 1}, {"Color": "creamy brown", "ID": 423, "Name": "Mexican Hot Chocolate", "Brands": ["Mexican Hot Chocolate"], "Category": 1}, {"Color": "brown", "ID": 248, "Name": "tea", "Brands": ["Tea Leaves", "Ice tea", "Iced tea", "English breakfast tea", "Tea"], "Category": 1}, {"Color": "brown", "ID": 298, "Name": "green tea", "Brands": ["Green tea bags", "Green tea"], "Category": 1}, {"Color": "brown", "ID": 354, "Name": "Lemon-Flavored Iced Tea", "Brands": ["Lemon-Flavored Iced Tea"], "Category": 1}, {"Color": "brown", "ID": 451, "Name": "Orange Pekoe Tea", "Brands": ["Orange Pekoe Tea"], "Category": 1}, {"Color": "brown", "ID": 588, "Name": "Snapple Raspberry Iced Tea", "Brands": ["Snapple Raspberry Iced Tea"], "Category": 1}, {"Color": "brown", "ID": 631, "Name": "Thai Tea", "Brands": ["Thai Tea"], "Category": 1}, {"Color": "brown", "ID": 638, "Name": "Turkish Apple Tea", "Brands": ["Turkish Apple Tea"], "Category": 1}, {"Color": "brown", "ID": 340, "Name": "Kiwi-Strawberry Snapple", "Brands": ["Kiwi-Strawberry Snapple"], "Category": 1}, {"Color": "brown", "ID": 587, "Name": "Snapple", "Brands": ["Snapple"], "Category": 1}, {"Color": "brown", "ID": 309, "Name": "Hard Apple Cider", "Brands": ["Hard apple cider"], "Category": 1}, {"Color": "yellow", "ID": 263, "Name": "Raspberry Lemonade", "Brands": ["Frozen raspberry lemonade concentrate", "Raspberry Lemonade"], "Category": 1}, {"Color": "yellow", "ID": 352, "Name": "lemonade", "Brands": ["Pink lemonade", "Lemonade"], "Category": 1}, {"Color": "yellow", "ID": 369, "Name": "Limeade", "Brands": ["Limeade"], "Category": 1}, {"Color": "yellow", "ID": 416, "Name": "Mello Yello", "Brands": ["Mellow Yello", "Mellow Yellow", "Mello Yello"], "Category": 1}, {"Color": "light blue", "ID": 81, "Name": "Tonic", "Brands": ["Tonic water", "Bitter lemon"], "Category": 1}, {"Color": "light blue", "ID": 572, "Name": "Schweppes Indian Tonic Water", "Brands": ["Schweppes Indian Tonic Water"], "Category": 1}, {"Color": "light blue", "ID": 574, "Name": "Schweppes Tonic Water", "Brands": ["Schweppes Tonic Water"], "Category": 1}, {"ID": 0, "Name": "Sprite", "Brands": ["7-Up", "Sprite", "Mountain Dew", "Diet 7-Up"], "Category": 2}, {"ID": 21, "Name": "almond syrup", "Brands": ["Orgeat syrup", "Almond extract", "Almond syrup"], "Category": 2}, {"ID": 23, "Name": "Almond", "Brands": ["Almonds"], "Category": 2}, {"ID": 31, "Name": "Anise plant", "Brands": ["Anise"], "Category": 2}, {"ID": 33, "Name": "Aperol aperitif", "Brands": ["Aperol"], "Category": 2}, {"ID": 35, "Name": "apple", "Brands": ["Granny Smith apple", "Apple"], "Category": 2}, {"ID": 39, "Name": "Applejack", "Brands": ["Applejack Brandy"], "Category": 2}, {"ID": 50, "Name": "radish", "Brands": ["Avignon radish", "Radish"], "Category": 2}, {"ID": 51, "Name": "Avocado", "Brands": ["Avocado"], "Category": 2}, {"ID": 52, "Name": "chocolate bitters", "Brands": ["Aztec chocolate bitters"], "Category": 2}, {"ID": 55, "Name": "Bacardi Breezer", "Brands": ["Bacardi Breezer"], "Category": 2}, {"ID": 62, "Name": "Irish Cream", "Brands": ["Irish cream", "Baileys Irish Cream"], "Category": 2}, {"ID": 64, "Name": "banana", "Brands": ["Banana"], "Category": 2}, {"ID": 67, "Name": "banana syrup", "Brands": ["Banana syrup"], "Category": 2}, {"ID": 68, "Name": "barbecue bitters", "Brands": ["Barbecue bitters"], "Category": 2}, {"ID": 71, "Name": "basil", "Brands": ["Basil"], "Category": 2}, {"ID": 74, "Name": "Becherovka bitters", "Brands": ["Becherovka"], "Category": 2}, {"ID": 75, "Name": "Beef Bouillon ", "Brands": ["Beef Bouillon"], "Category": 2}, {"ID": 77, "Name": "beef jerky", "Brands": ["Beef jerky"], "Category": 2}, {"ID": 79, "Name": "beets", "Brands": ["Beet juice"], "Category": 2}, {"ID": 82, "Name": "sour orange", "Brands": ["Seville orange", "Bitter orange", "Sour orange"], "Category": 2}, {"ID": 83, "Name": "blackberry", "Brands": ["Blackberries"], "Category": 2}, {"ID": 88, "Name": "cherry cola", "Brands": ["Black Cherry Cola", "Black Cherry Kool-Aid", "Cherry cola", "Cherry soda", "Cherry 7-up", "Cherryade"], "Category": 2}, {"ID": 89, "Name": "cherry jello", "Brands": ["Black Cherry Jello", "Cherry jello"], "Category": 2}, {"ID": 91, "Name": "black currant syrup", "Brands": ["Blackcurrant syrup"], "Category": 2}, {"ID": 93, "Name": "pepper", "Brands": ["Black pepper", "Red Pepper Flakes"], "Category": 2}, {"ID": 97, "Name": "blueberry", "Brands": ["Blueberries"], "Category": 2}, {"ID": 101, "Name": "blueberry syrup", "Brands": ["Blueberry syrup"], "Category": 2}, {"ID": 104, "Name": "blue food coloring", "Brands": ["Blue food coloring"], "Category": 2}, {"ID": 105, "Name": "blue hawaiian punch", "Brands": ["Blue hawaiian punch"], "Category": 2}, {"ID": 113, "Name": "sugar", "Brands": ["Sanding sugar", "Brown sugar", "White sugar", "Powdered sugar", "Sugar"], "Category": 2}, {"ID": 117, "Name": "butter", "Brands": ["Butter"], "Category": 2}, {"ID": 118, "Name": "pecan ice cream", "Brands": ["Butter pecan ice cream"], "Category": 2}, {"ID": 125, "Name": "campari", "Brands": ["Campari"], "Category": 2}, {"ID": 127, "Name": "candy", "Brands": ["Candy"], "Category": 2}, {"ID": 129, "Name": "cantaloupe", "Brands": ["Cantaloupe"], "Category": 2}, {"ID": 131, "Name": "coffee", "Brands": ["Coffee", "Cappuccino", "Instant coffee", "Espresso"], "Category": 2}, {"ID": 134, "Name": "caramel food coloring", "Brands": ["Caramel food coloring"], "Category": 2}, {"ID": 136, "Name": "caramel sauce", "Brands": ["Caramel sauce"], "Category": 2}, {"ID": 137, "Name": "caramel syrup", "Brands": ["Caramel syrup"], "Category": 2}, {"ID": 139, "Name": "caraway", "Brands": ["Caraway syrup", "Caraway", "Meridian Fennel", "Persian Cumin"], "Category": 2}, {"ID": 140, "Name": "mineral water", "Brands": ["Mineral water", "Perrier sparkling natural mineral water", "Carbonated water", "Seltzer water", "Sparkling water"], "Category": 2}, {"ID": 142, "Name": "cardamom", "Brands": ["Cardamom"], "Category": 2}, {"ID": 143, "Name": "cardamom bitters", "Brands": ["Cardamom bitters"], "Category": 2}, {"ID": 144, "Name": "Caribbean Cream ", "Brands": ["Caribbean Cream"], "Category": 2}, {"ID": 145, "Name": "carrot", "Brands": ["Carrot"], "Category": 2}, {"ID": 149, "Name": "celery", "Brands": ["Celery"], "Category": 2}, {"ID": 150, "Name": "celery bitters", "Brands": ["Celery bitters"], "Category": 2}, {"ID": 151, "Name": "celery salt", "Brands": ["Celery salt"], "Category": 2}, {"ID": 161, "Name": "cherry ice cream", "Brands": ["Cherry ice cream"], "Category": 2}, {"ID": 162, "Name": "cherry syrup", "Brands": ["Cherry syrup"], "Category": 2}, {"ID": 164, "Name": "chili powder", "Brands": ["Chili powder"], "Category": 2}, {"ID": 166, "Name": "chocolate ice cream", "Brands": ["Chocolate ice cream"], "Category": 2}, {"ID": 169, "Name": "chocolate sauce", "Brands": ["Chocolate sauce"], "Category": 2}, {"ID": 171, "Name": "chocolate syrup", "Brands": ["Chocolate syrup"], "Category": 2}, {"ID": 175, "Name": "cinnamon", "Brands": ["Ground cinnamon", "Cinnamon", "Cinnamon sticks"], "Category": 2}, {"ID": 181, "Name": "citrus-flavored energy drink", "Brands": ["Citrus Energy Drink"], "Category": 2}, {"ID": 183, "Name": "clove", "Brands": ["Clove"], "Category": 2}, {"ID": 184, "Name": "clove syrup", "Brands": ["Clove syrup"], "Category": 2}, {"ID": 188, "Name": "coconut", "Brands": ["Coconut"], "Category": 2}, {"ID": 191, "Name": "coconut syrup", "Brands": ["Coconut syrup"], "Category": 2}, {"ID": 193, "Name": "coffee ice cream", "Brands": ["Coffee ice cream"], "Category": 2}, {"ID": 199, "Name": "coriander", "Brands": ["Coriander"], "Category": 2}, {"ID": 200, "Name": "Cornstarch", "Brands": ["Cornstarch"], "Category": 2}, {"ID": 201, "Name": "corn syrup", "Brands": ["Corn syrup"], "Category": 2}, {"ID": 204, "Name": "cottage cheese", "Brands": ["Cottage cheese"], "Category": 2}, {"ID": 205, "Name": "cotton candy", "Brands": ["Yellow cotton candy", "Cotton candy"], "Category": 2}, {"ID": 206, "Name": "Cracker Jack", "Brands": ["Cracker jack"], "Category": 2}, {"ID": 208, "Name": "cranberry", "Brands": ["Cranberry"], "Category": 2}, {"ID": 214, "Name": "Creme de Cerise", "Brands": ["Creme de Cerise"], "Category": 2}, {"ID": 215, "Name": "Creme de Fraise", "Brands": ["Creme de Fraise"], "Category": 2}, {"ID": 216, "Name": "Creme de Mure", "Brands": ["Creme de Mure"], "Category": 2}, {"ID": 217, "Name": "Creme de Myrtille", "Brands": ["Creme de Myrtille"], "Category": 2}, {"ID": 218, "Name": "Creme de Noyaux", "Brands": ["Creme de Noyaux"], "Category": 2}, {"ID": 219, "Name": "creme de peche", "Brands": ["Creme de peche"], "Category": 2}, {"ID": 220, "Name": "Creme de Violette", "Brands": ["Creme de Violette"], "Category": 2}, {"ID": 228, "Name": "Cynar", "Brands": ["Cynar"], "Category": 2}, {"ID": 230, "Name": "pimento bitters", "Brands": ["Dale DeGroff's Pimento Bitters", "Pimento bitters"], "Category": 2}, {"ID": 231, "Name": "Danzig Goldwasser", "Brands": ["Danzig Goldwasser"], "Category": 2}, {"ID": 232, "Name": "chocolate chips", "Brands": ["Dark chocolate chips"], "Category": 2}, {"ID": 233, "Name": "DeKuyper Island Blue Pucker", "Brands": ["DeKuyper Island Blue Pucker"], "Category": 2}, {"ID": 234, "Name": "raspberry", "Brands": ["Fresh raspberries", "DeKuyper Peachtree Schnapps", "Raspberry"], "Category": 2}, {"ID": 237, "Name": "Dr Pepper", "Brands": ["Diet Dr Pepper", "Dr pepper"], "Category": 2}, {"ID": 238, "Name": "Dill", "Brands": ["Dill"], "Category": 2}, {"ID": 242, "Name": "Dubonnet aperitif", "Brands": ["Dubonnet", "Dubonnet Blanc", "Dubonnet Rouge"], "Category": 2}, {"ID": 243, "Name": "edible flowers", "Brands": ["Edible flowers"], "Category": 2}, {"ID": 244, "Name": "egg", "Brands": ["Egg"], "Category": 2}, {"ID": 245, "Name": "eggnog", "Brands": ["Eggnog"], "Category": 2}, {"ID": 246, "Name": "Elderflower Cordial", "Brands": ["Elderflower Cordial", "St Germain"], "Category": 2}, {"ID": 247, "Name": "Energy Drink", "Brands": ["Energy Drink"], "Category": 2}, {"ID": 250, "Name": "Everclear 151 Grain Alcohol ", "Brands": ["Everclear 151 Grain Alcohol"], "Category": 2}, {"ID": 251, "Name": "Fennel Seeds", "Brands": ["Fennel Seeds"], "Category": 2}, {"ID": 257, "Name": "Fisherman's Friend", "Brands": ["Fisherman's Friend"], "Category": 2}, {"ID": 258, "Name": "Five Alive", "Brands": ["Five Alive"], "Category": 2}, {"ID": 259, "Name": "Food Coloring", "Brands": ["Food Coloring"], "Category": 2}, {"ID": 261, "Name": "Fresca", "Brands": ["Fresca"], "Category": 2}, {"ID": 262, "Name": "peppercorn", "Brands": ["Freshly ground pink peppercorn", "Peppercorn"], "Category": 2}, {"ID": 264, "Name": "Fruit", "Brands": ["Fruit"], "Category": 2}, {"ID": 265, "Name": "Fruit Cocktail", "Brands": ["Fruit Cocktail"], "Category": 2}, {"ID": 268, "Name": "Fruit Punch", "Brands": ["Gatorade Fruit Punch", "Fruit punch", "Tropicana Fruit Punch", "Minute Maid Fruit Punch", "Orange-Banana Fruit Punch"], "Category": 2}, {"ID": 269, "Name": "Fruits", "Brands": ["Fruits"], "Category": 2}, {"ID": 272, "Name": "fruit syrup", "Brands": ["Fruit syrup"], "Category": 2}, {"ID": 273, "Name": "Fudge Ice Cream", "Brands": ["Fudge Ice Cream"], "Category": 2}, {"ID": 275, "Name": "Gatorade", "Brands": ["Gatorade"], "Category": 2}, {"ID": 276, "Name": "Gelatin", "Brands": ["Gelatin"], "Category": 2}, {"ID": 282, "Name": "Graham Crackers", "Brands": ["Graham Crackers"], "Category": 2}, {"ID": 283, "Name": "Grain Alcohol", "Brands": ["Grain Alcohol"], "Category": 2}, {"ID": 284, "Name": "Grapefruit", "Brands": ["Grapefruit"], "Category": 2}, {"ID": 285, "Name": "Grapefruit Bitters", "Brands": ["Grapefruit bitters"], "Category": 2}, {"ID": 290, "Name": "grapes", "Brands": ["Grapes"], "Category": 2}, {"ID": 294, "Name": "Green Apple", "Brands": ["Green Apple"], "Category": 2}, {"ID": 295, "Name": "bell pepper", "Brands": ["Green bell pepper"], "Category": 2}, {"ID": 296, "Name": "Green Food Coloring", "Brands": ["Green Food Coloring"], "Category": 2}, {"ID": 300, "Name": "ground allspice", "Brands": ["Ground allspice"], "Category": 2}, {"ID": 304, "Name": "Guava Syrup", "Brands": ["Guava Syrup"], "Category": 2}, {"ID": 306, "Name": "Gummi Bears", "Brands": ["Gummi Bears"], "Category": 2}, {"ID": 307, "Name": "hot pepper", "Brands": ["Habanero pepper"], "Category": 2}, {"ID": 311, "Name": "hazelnut syrup", "Brands": ["Hazelnut syrup"], "Category": 2}, {"ID": 315, "Name": "honey", "Brands": ["Honey"], "Category": 2}, {"ID": 316, "Name": "Honeydew Melon", "Brands": ["Honeydew Melon"], "Category": 2}, {"ID": 317, "Name": "Honey Syrup", "Brands": ["Honey Syrup"], "Category": 2}, {"ID": 319, "Name": "Horseradish", "Brands": ["Horseradish"], "Category": 2}, {"ID": 320, "Name": "Horseradish Sauce", "Brands": ["Horseradish Sauce"], "Category": 2}, {"ID": 322, "Name": "ice", "Brands": ["Ice"], "Category": 2}, {"ID": 323, "Name": "ice cream", "Brands": ["Ice cream", "Vanilla ice cream"], "Category": 2}, {"ID": 328, "Name": "jalapeno", "Brands": ["Jalapeno pepper", "Jalapeno"], "Category": 2}, {"ID": 329, "Name": "Jello", "Brands": ["Jello"], "Category": 2}, {"ID": 333, "Name": "Jolt Cola", "Brands": ["Jolt Cola"], "Category": 2}, {"ID": 334, "Name": "kale", "Brands": ["Kale"], "Category": 2}, {"ID": 335, "Name": "Kiwi", "Brands": ["Kiwi"], "Category": 2}, {"ID": 338, "Name": "Kiwis", "Brands": ["Kiwis"], "Category": 2}, {"ID": 341, "Name": "Kiwi Syrup", "Brands": ["Kiwi Syrup"], "Category": 2}, {"ID": 342, "Name": "kombu seaweed", "Brands": ["Kombu seaweed"], "Category": 2}, {"ID": 344, "Name": "Kummel", "Brands": ["Kummel"], "Category": 2}, {"ID": 345, "Name": "Kumquat", "Brands": ["Kumquat"], "Category": 2}, {"ID": 346, "Name": "Lager", "Brands": ["Lager"], "Category": 2}, {"ID": 349, "Name": "lavender", "Brands": ["Lavender"], "Category": 2}, {"ID": 351, "Name": "Lemon", "Brands": ["Lemon"], "Category": 2}, {"ID": 355, "Name": "Lemon Italian Ice", "Brands": ["Lemon Italian Ice"], "Category": 2}, {"ID": 361, "Name": "Lemon Sherbet", "Brands": ["Lemon Sherbet"], "Category": 2}, {"ID": 363, "Name": "Lemon Syrup", "Brands": ["Lemon Syrup"], "Category": 2}, {"ID": 366, "Name": "Lilikoi Syrup", "Brands": ["Lilikoi Syrup"], "Category": 2}, {"ID": 368, "Name": "lime", "Brands": ["Lime"], "Category": 2}, {"ID": 372, "Name": "Lime Ice", "Brands": ["Lime Ice"], "Category": 2}, {"ID": 373, "Name": "Lime Jello", "Brands": ["Lime Jello"], "Category": 2}, {"ID": 378, "Name": "Lime Peel", "Brands": ["Lime Peel"], "Category": 2}, {"ID": 379, "Name": "Lime Sherbet", "Brands": ["Lime Sherbet"], "Category": 2}, {"ID": 381, "Name": "Lime Syrup", "Brands": ["Lime Syrup"], "Category": 2}, {"ID": 384, "Name": "Lingonberry Jam", "Brands": ["Lingonberry Jam"], "Category": 2}, {"ID": 387, "Name": "Louisiana Hot Sauce", "Brands": ["Louisiana Hot Sauce"], "Category": 2}, {"ID": 388, "Name": "Lychee", "Brands": ["Lychee"], "Category": 2}, {"ID": 392, "Name": "Mace", "Brands": ["Mace"], "Category": 2}, {"ID": 399, "Name": "mango", "Brands": ["Mango"], "Category": 2}, {"ID": 405, "Name": "Mango Sherbet", "Brands": ["Mango Sherbet"], "Category": 2}, {"ID": 407, "Name": "Mango Syrup", "Brands": ["Mango Syrup"], "Category": 2}, {"ID": 408, "Name": "Maple Syrup", "Brands": ["Maple Syrup"], "Category": 2}, {"ID": 410, "Name": "Maracuja Syrup", "Brands": ["Maracuja Syrup"], "Category": 2}, {"ID": 411, "Name": "marijuana", "Brands": ["Pot", "Marijuana", "Marijuana bud"], "Category": 2}, {"ID": 412, "Name": "Marjoram", "Brands": ["Marjoram"], "Category": 2}, {"ID": 413, "Name": "Marmalade", "Brands": ["Marmalade"], "Category": 2}, {"ID": 414, "Name": "Marshmallows", "Brands": ["Marshmallows"], "Category": 2}, {"ID": 417, "Name": "Watermelon", "Brands": ["Melon", "Watermelon Juice", "Watermelon"], "Category": 2}, {"ID": 422, "Name": "Mexican Chocolate", "Brands": ["Mexican Chocolate"], "Category": 2}, {"ID": 426, "Name": "mint", "Brands": ["Mint leaves"], "Category": 2}, {"ID": 428, "Name": "Mint Syrup", "Brands": ["Mint Syrup"], "Category": 2}, {"ID": 429, "Name": "Molasses", "Brands": ["Pomegranate molasses", "Molasses"], "Category": 2}, {"ID": 430, "Name": "Monster energy drink", "Brands": ["Monster energy drink"], "Category": 2}, {"ID": 432, "Name": "Nutella", "Brands": ["Nutella"], "Category": 2}, {"ID": 433, "Name": "nutmeg", "Brands": ["Nutmeg"], "Category": 2}, {"ID": 434, "Name": "Nuts", "Brands": ["Nuts"], "Category": 2}, {"ID": 435, "Name": "Ojen", "Brands": ["Ojen"], "Category": 2}, {"ID": 436, "Name": "olive", "Brands": ["Olive"], "Category": 2}, {"ID": 437, "Name": "olive brine", "Brands": ["Olive brine"], "Category": 2}, {"ID": 439, "Name": "Olives", "Brands": ["Olives"], "Category": 2}, {"ID": 440, "Name": "Onion", "Brands": ["Onion"], "Category": 2}, {"ID": 441, "Name": "orange", "Brands": ["Orange"], "Category": 2}, {"ID": 442, "Name": "Orangeade", "Brands": ["Orangeade"], "Category": 2}, {"ID": 445, "Name": "orange flower water", "Brands": ["Orange flower water"], "Category": 2}, {"ID": 447, "Name": "Orange Ice", "Brands": ["Orange Ice"], "Category": 2}, {"ID": 448, "Name": "Orange Jello", "Brands": ["Orange Jello"], "Category": 2}, {"ID": 452, "Name": "Orange Sherbet", "Brands": ["Orange Sherbet"], "Category": 2}, {"ID": 453, "Name": "Orange spiral", "Brands": ["Orange spiral"], "Category": 2}, {"ID": 454, "Name": "Orange Syrup", "Brands": ["Orange Syrup"], "Category": 2}, {"ID": 456, "Name": "orange zest", "Brands": ["Orange zest"], "Category": 2}, {"ID": 458, "Name": "oregano", "Brands": ["Oregano"], "Category": 2}, {"ID": 459, "Name": "oreo cookie", "Brands": ["Oreo cookie"], "Category": 2}, {"ID": 461, "Name": "Papaya", "Brands": ["Papaya"], "Category": 2}, {"ID": 464, "Name": "paprika", "Brands": ["Spicy paprika", "Paprika"], "Category": 2}, {"ID": 465, "Name": "parfait d'amour", "Brands": ["Parfait d'amour"], "Category": 2}, {"ID": 466, "Name": "Passion-fruit", "Brands": ["Passion-fruit"], "Category": 2}, {"ID": 470, "Name": "passionfruit syrup", "Brands": ["Passionfruit syrup", "Passionfruit puree"], "Category": 2}, {"ID": 471, "Name": "Passion-fruit Syrup", "Brands": ["Passion-fruit Syrup"], "Category": 2}, {"ID": 472, "Name": "Passoa", "Brands": ["Passoa"], "Category": 2}, {"ID": 473, "Name": "Pastis", "Brands": ["Pastis"], "Category": 2}, {"ID": 475, "Name": "peach bitters", "Brands": ["Peach bitters"], "Category": 2}, {"ID": 477, "Name": "Peach", "Brands": ["Peaches"], "Category": 2}, {"ID": 480, "Name": "Peach Passion-Fruit Jello", "Brands": ["Peach Passion-Fruit Jello"], "Category": 2}, {"ID": 481, "Name": "Peach Puree", "Brands": ["Peach Puree"], "Category": 2}, {"ID": 482, "Name": "Peach Sherbet", "Brands": ["Peach Sherbet"], "Category": 2}, {"ID": 484, "Name": "Peanut Butter", "Brands": ["Peanut Butter"], "Category": 2}, {"ID": 486, "Name": "pear", "Brands": ["Pear"], "Category": 2}, {"ID": 493, "Name": "Pecans", "Brands": ["Pecans"], "Category": 2}, {"ID": 494, "Name": "Pecher Mignon", "Brands": ["Pecher Mignon"], "Category": 2}, {"ID": 495, "Name": "Pepper", "Brands": ["Pepper"], "Category": 2}, {"ID": 496, "Name": "Peppermint Extract", "Brands": ["Peppermint Extract"], "Category": 2}, {"ID": 499, "Name": "Peppermint Syrup", "Brands": ["Peppermint Syrup"], "Category": 2}, {"ID": 500, "Name": "Peppers", "Brands": ["Peppers"], "Category": 2}, {"ID": 501, "Name": "Pepper Sauce", "Brands": ["Pepper Sauce"], "Category": 2}, {"ID": 502, "Name": "Peychaud's Bitters", "Brands": ["Peychaud's Bitters"], "Category": 2}, {"ID": 505, "Name": "Pimm's No.1", "Brands": ["Pimm's No.1"], "Category": 2}, {"ID": 509, "Name": "Pineapple", "Brands": ["Pineapple"], "Category": 2}, {"ID": 511, "Name": "Pineapple Sherbet", "Brands": ["Pineapple Sherbet"], "Category": 2}, {"ID": 513, "Name": "Pineapple Syrup", "Brands": ["Pineapple Syrup"], "Category": 2}, {"ID": 520, "Name": "Pistachio Ice Cream", "Brands": ["Pistachio Ice Cream"], "Category": 2}, {"ID": 524, "Name": "Plums", "Brands": ["Plums"], "Category": 2}, {"ID": 528, "Name": "Popsicle", "Brands": ["Popsicle"], "Category": 2}, {"ID": 532, "Name": "Pumpkin", "Brands": ["Pumpkin puree", "Pumpkin"], "Category": 2}, {"ID": 535, "Name": "Pumpkin Spice", "Brands": ["Pumpkin spice"], "Category": 2}, {"ID": 536, "Name": "Punt e Mes", "Brands": ["Punt e Mes"], "Category": 2}, {"ID": 537, "Name": "Rainbow Sherbet", "Brands": ["Rainbow Sherbet"], "Category": 2}, {"ID": 538, "Name": "Raisins", "Brands": ["Raisins"], "Category": 2}, {"ID": 540, "Name": "Raspberry Cordial", "Brands": ["Raspberry Cordial"], "Category": 2}, {"ID": 541, "Name": "Raspberry Ice Cream", "Brands": ["Raspberry Ice Cream"], "Category": 2}, {"ID": 542, "Name": "Raspberry Jam", "Brands": ["Raspberry Jam"], "Category": 2}, {"ID": 544, "Name": "Raspberry Puree", "Brands": ["Raspberry Puree"], "Category": 2}, {"ID": 546, "Name": "Raspberry Sherbet", "Brands": ["Raspberry Sherbet"], "Category": 2}, {"ID": 548, "Name": "raspberry syrup", "Brands": ["Raspberry syrup"], "Category": 2}, {"ID": 550, "Name": "Raspberry Yogurt", "Brands": ["Raspberry Yogurt"], "Category": 2}, {"ID": 551, "Name": "Red Bull", "Brands": ["Red Bull"], "Category": 2}, {"ID": 552, "Name": "red devil", "Brands": ["Red Devil"], "Category": 2}, {"ID": 553, "Name": "Red Food Coloring", "Brands": ["Red Food Coloring"], "Category": 2}, {"ID": 557, "Name": "Rhubarb", "Brands": ["Rhubarb"], "Category": 2}, {"ID": 558, "Name": "rhubarb bitters", "Brands": ["Rhubarb bitters"], "Category": 2}, {"ID": 559, "Name": "Ricard", "Brands": ["Ricard"], "Category": 2}, {"ID": 560, "Name": "Rockstar energy drink", "Brands": ["Rockstar energy drink"], "Category": 2}, {"ID": 561, "Name": "root beer", "Brands": ["Root beer"], "Category": 2}, {"ID": 562, "Name": "rosemary", "Brands": ["Rosemary simple syrup", "Rosemary"], "Category": 2}, {"ID": 563, "Name": "Rosewater", "Brands": ["Rosewater"], "Category": 2}, {"ID": 567, "Name": "salsa", "Brands": ["Salsa verde"], "Category": 2}, {"ID": 568, "Name": "salt", "Brands": ["Sea salt", "Salt"], "Category": 2}, {"ID": 569, "Name": "Sangria", "Brands": ["Sangria"], "Category": 2}, {"ID": 570, "Name": "Sarsaparilla", "Brands": ["Sarsaparilla"], "Category": 2}, {"ID": 571, "Name": "Sauternes", "Brands": ["Sauternes"], "Category": 2}, {"ID": 573, "Name": "Schweppes Russian", "Brands": ["Schweppes Russian"], "Category": 2}, {"ID": 575, "Name": "Sherbet", "Brands": ["Sherbet"], "Category": 2}, {"ID": 578, "Name": "simple syrup", "Brands": ["Sugar syrup", "Simple syrup"], "Category": 2}, {"ID": 580, "Name": "Smirnoff Green Apple Twist", "Brands": ["Smirnoff Green Apple Twist"], "Category": 2}, {"ID": 581, "Name": "Smirnoff Ice", "Brands": ["Smirnoff Ice"], "Category": 2}, {"ID": 585, "Name": "Smirnoff Watermelon Twist", "Brands": ["Smirnoff Watermelon Twist"], "Category": 2}, {"ID": 586, "Name": "snap peas", "Brands": ["Snap peas", "Sugar snap pea pods"], "Category": 2}, {"ID": 589, "Name": "Sour Apple", "Brands": ["Sour Apple"], "Category": 2}, {"ID": 590, "Name": "Sour Apple Jello", "Brands": ["Sour Apple Jello"], "Category": 2}, {"ID": 592, "Name": "Soy Sauce", "Brands": ["Soy Sauce"], "Category": 2}, {"ID": 595, "Name": "spiced demerara syrup", "Brands": ["Spiced demerara syrup"], "Category": 2}, {"ID": 598, "Name": "Squirt", "Brands": ["Squirt"], "Category": 2}, {"ID": 600, "Name": "Stout", "Brands": ["Stout"], "Category": 2}, {"ID": 601, "Name": "strawberry", "Brands": ["Strawberry", "Strawberry juice"], "Category": 2}, {"ID": 605, "Name": "Strawberry Ice Cream", "Brands": ["Strawberry Ice Cream"], "Category": 2}, {"ID": 606, "Name": "Strawberry Jello", "Brands": ["Strawberry Jello"], "Category": 2}, {"ID": 612, "Name": "strawberry syrup", "Brands": ["Strawberry syrup"], "Category": 2}, {"ID": 614, "Name": "Strawberry Yogurt", "Brands": ["Strawberry Yogurt"], "Category": 2}, {"ID": 615, "Name": "Strega", "Brands": ["Strega"], "Category": 2}, {"ID": 617, "Name": "Sunny Delight", "Brands": ["Sunny Delight"], "Category": 2}, {"ID": 618, "Name": "Swedish Punsch", "Brands": ["Swedish Punsch"], "Category": 2}, {"ID": 619, "Name": "Sweet and Sour Sauce", "Brands": ["Sweet and Sour Sauce"], "Category": 2}, {"ID": 621, "Name": "Swiss Chocolate Almond", "Brands": ["Swiss Chocolate Almond"], "Category": 2}, {"ID": 622, "Name": "Syrup", "Brands": ["Syrup"], "Category": 2}, {"ID": 623, "Name": "Syrup of Roses", "Brands": ["Syrup of Roses"], "Category": 2}, {"ID": 624, "Name": "Tabasco sauce", "Brands": ["Tabasco", "Tabasco sauce"], "Category": 2}, {"ID": 627, "Name": "Tang", "Brands": ["Tang"], "Category": 2}, {"ID": 630, "Name": "tarragon", "Brands": ["Tarragon", "Tarragon leaves"], "Category": 2}, {"ID": 632, "Name": "thyme", "Brands": ["Thyme"], "Category": 2}, {"ID": 633, "Name": "Triple Sec", "Brands": ["Triple Sec"], "Category": 2}, {"ID": 635, "Name": "Tropical Fruit", "Brands": ["Tropical Fruit"], "Category": 2}, {"ID": 639, "Name": "Underberg Bitters", "Brands": ["Underberg Bitters"], "Category": 2}, {"ID": 640, "Name": "Van Der Hum", "Brands": ["Van Der Hum"], "Category": 2}, {"ID": 642, "Name": "Vanilla", "Brands": ["Vanilla beans", "Vanilla"], "Category": 2}, {"ID": 643, "Name": "Vanilla Bean", "Brands": ["Vanilla Bean"], "Category": 2}, {"ID": 645, "Name": "Vanilla Extract", "Brands": ["Vanilla Extract"], "Category": 2}, {"ID": 648, "Name": "Vanilla Sugar", "Brands": ["Vanilla Sugar"], "Category": 2}, {"ID": 649, "Name": "Vanilla Syrup", "Brands": ["Vanilla Sugar Syrup", "Vanilla Syrup"], "Category": 2}, {"ID": 650, "Name": "Veev Acai Liquor", "Brands": ["Veev"], "Category": 2}, {"ID": 652, "Name": "vinegar", "Brands": ["Vinegar"], "Category": 2}, {"ID": 654, "Name": "water", "Brands": ["Water"], "Category": 2}, {"ID": 656, "Name": "Watermelon Jello", "Brands": ["Watermelon Jello"], "Category": 2}, {"ID": 657, "Name": "Watermelons", "Brands": ["Watermelons"], "Category": 2}, {"ID": 660, "Name": "whipped cream", "Brands": ["Whipped topping", "Whipped cream"], "Category": 2}, {"ID": 661, "Name": "White Chocolate", "Brands": ["White Chocolate"], "Category": 2}, {"ID": 663, "Name": "White Food Coloring", "Brands": ["White Food Coloring"], "Category": 2}, {"ID": 664, "Name": "White Pineau des Charentes", "Brands": ["White Pineau des Charentes"], "Category": 2}, {"ID": 669, "Name": "Worcestershire sauce", "Brands": ["Worcestershire sauce"], "Category": 2}, {"ID": 670, "Name": "Wormwood", "Brands": ["Wormwood"], "Category": 2}, {"ID": 671, "Name": "Wormwood Extract", "Brands": ["Wormwood Extract"], "Category": 2}, {"ID": 672, "Name": "yeast", "Brands": ["Yeast"], "Category": 2}, {"ID": 673, "Name": "Yellow Food Coloring", "Brands": ["Yellow Food Coloring"], "Category": 2}, {"ID": 674, "Name": "yogurt", "Brands": ["Yogurt"], "Category": 2}, {"ID": 675, "Name": "Yukon Jack", "Brands": ["Yukon Jack"], "Category": 2}]